region_selection/__init__.py
region_selection/region_selection.py
region_selection_apr-0.1.0.dist-info/LICENSE
region_selection_apr-0.1.0.dist-info/METADATA
region_selection_apr-0.1.0.dist-info/WHEEL
region_selection_apr-0.1.0.dist-info/top_level.txt
region_selection_apr-0.1.0.dist-info/RECORD
