Metadata-Version: 2.1
Name: region-selection-apr
Version: 0.1.0
Summary: Methods for filtering for high-scoring genomic intervals
Home-page: https://github.com/alexpreynolds/region-selection
Author: Alex Reynolds, Jacob Quon, and Wouter Meuleman
Author-email: alexpreynolds@gmail.com
Project-URL: Bug Tracker, https://github.com/alexpreynolds/region-selection/issues
Classifier: Programming Language :: Python :: 3
Classifier: License :: OSI Approved :: MIT License
Classifier: Operating System :: OS Independent
Requires-Python: >=3.7
License-File: LICENSE
Requires-Dist: pyranges (>=0.0.115)
Requires-Dist: numpy (>=1.20.3)
Requires-Dist: pandas (>=1.2.4)
Requires-Dist: click (>=8.0.0)
Requires-Dist: bottleneck (>=1.3.2)
